jko_loggers/__init__.py
jko_loggers/loggers.py
jko_loggers-0.0.1.dist-info/METADATA
jko_loggers-0.0.1.dist-info/RECORD
jko_loggers-0.0.1.dist-info/WHEEL
jko_loggers-0.0.1.dist-info/top_level.txt
